
{
"result":{
"query":":facetid:toc:\"db/conf/cpm/cpm2020.bht\"",
"status":{
"@code":"200",
"text":"OK"
},
"time":{
"@unit":"msecs",
"text":"115.23"
},
"completions":{
"@total":"1",
"@computed":"1",
"@sent":"1",
"c":{
"@sc":"31",
"@dc":"31",
"@oc":"31",
"@id":"35338751",
"text":":facetid:toc:db/conf/cpm/cpm2020.bht"
}
},
"hits":{
"@total":"31",
"@computed":"31",
"@sent":"31",
"@first":"0",
"hit":[{
"@score":"1",
"@id":"629772",
"info":{"authors":{"author":[{"@pid":"11/495-1","text":"Giulia Bernardini 0001"},{"@pid":"80/4509","text":"Paola Bonizzoni"},{"@pid":"49/3088","text":"Pawel Gawrychowski"}]},"title":"On Two Measures of Distance Between Fully-Labelled Trees.","venue":"CPM","pages":"6:1-6:16","year":"2020","type":"Conference and Workshop Papers","access":"open","key":"conf/cpm/0001BG20","doi":"10.4230/LIPICS.CPM.2020.6","ee":"https://doi.org/10.4230/LIPIcs.CPM.2020.6","url":"https://dblp.org/rec/conf/cpm/0001BG20"},
"url":"URL#629772"
},
{
"@score":"1",
"@id":"629773",
"info":{"authors":{"author":[{"@pid":"11/495-1","text":"Giulia Bernardini 0001"},{"@pid":"23/2916","text":"Huiping Chen"},{"@pid":"96/4724","text":"Grigorios Loukides"},{"@pid":"p/NadiaPisanti","text":"Nadia Pisanti"},{"@pid":"89/7966","text":"Solon P. Pissis"},{"@pid":"05/1060","text":"Leen Stougie"},{"@pid":"266/9278","text":"Michelle Sweering"}]},"title":"String Sanitization Under Edit Distance.","venue":"CPM","pages":"7:1-7:14","year":"2020","type":"Conference and Workshop Papers","access":"open","key":"conf/cpm/0001CLPPSS20","doi":"10.4230/LIPICS.CPM.2020.7","ee":"https://doi.org/10.4230/LIPIcs.CPM.2020.7","url":"https://dblp.org/rec/conf/cpm/0001CLPPSS20"},
"url":"URL#629773"
},
{
"@score":"1",
"@id":"629774",
"info":{"authors":{"author":[{"@pid":"116/4616-2","text":"Arnab Ganguly 0002"},{"@pid":"225/3576","text":"Daniel Gibney"},{"@pid":"160/8206","text":"Sahar Hooshmand"},{"@pid":"32/317","text":"M. Oguzhan Külekci"},{"@pid":"99/7237","text":"Sharma V. Thankachan"}]},"title":"FM-Index Reveals the Reverse Suffix Array.","venue":"CPM","pages":"13:1-13:14","year":"2020","type":"Conference and Workshop Papers","access":"open","key":"conf/cpm/0002GHKT20","doi":"10.4230/LIPICS.CPM.2020.13","ee":"https://doi.org/10.4230/LIPIcs.CPM.2020.13","url":"https://dblp.org/rec/conf/cpm/0002GHKT20"},
"url":"URL#629774"
},
{
"@score":"1",
"@id":"629775",
"info":{"authors":{"author":[{"@pid":"198/1439","text":"Mai Alzamel"},{"@pid":"164/5849","text":"Alessio Conte"},{"@pid":"97/10871","text":"Shuhei Denzumi"},{"@pid":"g/RobertoGrossi","text":"Roberto Grossi"},{"@pid":"i/CSIliopoulos","text":"Costas S. Iliopoulos"},{"@pid":"203/8082","text":"Kazuhiro Kurita"},{"@pid":"117/5870","text":"Kunihiro Wasa"}]},"title":"Finding the Anticover of a String.","venue":"CPM","pages":"2:1-2:11","year":"2020","type":"Conference and Workshop Papers","access":"open","key":"conf/cpm/AlzamelCDGIKW20","doi":"10.4230/LIPICS.CPM.2020.2","ee":"https://doi.org/10.4230/LIPIcs.CPM.2020.2","url":"https://dblp.org/rec/conf/cpm/AlzamelCDGIKW20"},
"url":"URL#629775"
},
{
"@score":"1",
"@id":"629776",
"info":{"authors":{"author":[{"@pid":"a/AAmir","text":"Amihood Amir"},{"@pid":"32/3746","text":"Ayelet Butman"},{"@pid":"l/GadMLandau","text":"Gad M. Landau"},{"@pid":"04/8240","text":"Shoshana Marcus"},{"@pid":"91/3705","text":"Dina Sokol"}]},"title":"Double String Tandem Repeats.","venue":"CPM","pages":"3:1-3:13","year":"2020","type":"Conference and Workshop Papers","access":"open","key":"conf/cpm/AmirBLMS20","doi":"10.4230/LIPICS.CPM.2020.3","ee":"https://doi.org/10.4230/LIPIcs.CPM.2020.3","url":"https://dblp.org/rec/conf/cpm/AmirBLMS20"},
"url":"URL#629776"
},
{
"@score":"1",
"@id":"629777",
"info":{"authors":{"author":[{"@pid":"70/4285","text":"Djamal Belazzougui"},{"@pid":"k/GregoryKucherov","text":"Gregory Kucherov"}]},"title":"Efficient Tree-Structured Categorical Retrieval.","venue":"CPM","pages":"4:1-4:11","year":"2020","type":"Conference and Workshop Papers","access":"open","key":"conf/cpm/BelazzouguiK20","doi":"10.4230/LIPICS.CPM.2020.4","ee":"https://doi.org/10.4230/LIPIcs.CPM.2020.4","url":"https://dblp.org/rec/conf/cpm/BelazzouguiK20"},
"url":"URL#629777"
},
{
"@score":"1",
"@id":"629778",
"info":{"authors":{"author":[{"@pid":"184/0588","text":"Panagiotis Charalampopoulos"},{"@pid":"38/9892","text":"Tomasz Kociumaka"},{"@pid":"51/4682","text":"Manal Mohamed 0001"},{"@pid":"83/7216","text":"Jakub Radoszewski"},{"@pid":"r/WojciechRytter","text":"Wojciech Rytter"},{"@pid":"223/9993","text":"Juliusz Straszynski"},{"@pid":"80/5679","text":"Tomasz Walen"},{"@pid":"223/9846","text":"Wiktor Zuba"}]},"title":"Counting Distinct Patterns in Internal Dictionary Matching.","venue":"CPM","pages":"8:1-8:15","year":"2020","type":"Conference and Workshop Papers","access":"open","key":"conf/cpm/Charalampopoulos20","doi":"10.4230/LIPICS.CPM.2020.8","ee":"https://doi.org/10.4230/LIPIcs.CPM.2020.8","url":"https://dblp.org/rec/conf/cpm/Charalampopoulos20"},
"url":"URL#629778"
},
{
"@score":"1",
"@id":"629779",
"info":{"authors":{"author":[{"@pid":"184/0588","text":"Panagiotis Charalampopoulos"},{"@pid":"38/9892","text":"Tomasz Kociumaka"},{"@pid":"35/6579","text":"Shay Mozes"}]},"title":"Dynamic String Alignment.","venue":"CPM","pages":"9:1-9:13","year":"2020","type":"Conference and Workshop Papers","access":"open","key":"conf/cpm/Charalampopoulos20a","doi":"10.4230/LIPICS.CPM.2020.9","ee":"https://doi.org/10.4230/LIPIcs.CPM.2020.9","url":"https://dblp.org/rec/conf/cpm/Charalampopoulos20a"},
"url":"URL#629779"
},
{
"@score":"1",
"@id":"629780",
"info":{"authors":{"author":[{"@pid":"184/0588","text":"Panagiotis Charalampopoulos"},{"@pid":"89/7966","text":"Solon P. Pissis"},{"@pid":"83/7216","text":"Jakub Radoszewski"},{"@pid":"80/5679","text":"Tomasz Walen"},{"@pid":"223/9846","text":"Wiktor Zuba"}]},"title":"Unary Words Have the Smallest Levenshtein k-Neighbourhoods.","venue":"CPM","pages":"10:1-10:12","year":"2020","type":"Conference and Workshop Papers","access":"open","key":"conf/cpm/Charalampopoulos20b","doi":"10.4230/LIPICS.CPM.2020.10","ee":"https://doi.org/10.4230/LIPIcs.CPM.2020.10","url":"https://dblp.org/rec/conf/cpm/Charalampopoulos20b"},
"url":"URL#629780"
},
{
"@score":"1",
"@id":"629781",
"info":{"authors":{"author":[{"@pid":"263/2890","text":"Patty Commins"},{"@pid":"34/5224","text":"David Liben-Nowell"},{"@pid":"12/5132","text":"Tina Liu"},{"@pid":"234/3203","text":"Kiran Tomlinson"}]},"title":"Summarizing Diverging String Sequences, with Applications to Chain-Letter Petitions.","venue":"CPM","pages":"11:1-11:15","year":"2020","type":"Conference and Workshop Papers","access":"open","key":"conf/cpm/ComminsLLT20","doi":"10.4230/LIPICS.CPM.2020.11","ee":"https://doi.org/10.4230/LIPIcs.CPM.2020.11","url":"https://dblp.org/rec/conf/cpm/ComminsLLT20"},
"url":"URL#629781"
},
{
"@score":"1",
"@id":"629782",
"info":{"authors":{"author":[{"@pid":"219/5876","text":"Mitsuru Funakoshi"},{"@pid":"118/6656","text":"Yuto Nakashima"},{"@pid":"88/1129","text":"Shunsuke Inenaga"},{"@pid":"44/2355","text":"Hideo Bannai"},{"@pid":"35/1544","text":"Masayuki Takeda"},{"@pid":"s/AyumiShinohara","text":"Ayumi Shinohara"}]},"title":"Detecting k-(Sub-)Cadences and Equidistant Subsequence Occurrences.","venue":"CPM","pages":"12:1-12:11","year":"2020","type":"Conference and Workshop Papers","access":"open","key":"conf/cpm/FunakoshiNIBTS20","doi":"10.4230/LIPICS.CPM.2020.12","ee":"https://doi.org/10.4230/LIPIcs.CPM.2020.12","url":"https://dblp.org/rec/conf/cpm/FunakoshiNIBTS20"},
"url":"URL#629782"
},
{
"@score":"1",
"@id":"629783",
"info":{"authors":{"author":[{"@pid":"49/3088","text":"Pawel Gawrychowski"},{"@pid":"266/8919","text":"Samah Ghazawi"},{"@pid":"l/GadMLandau","text":"Gad M. Landau"}]},"title":"On Indeterminate Strings Matching.","venue":"CPM","pages":"14:1-14:14","year":"2020","type":"Conference and Workshop Papers","access":"open","key":"conf/cpm/GawrychowskiGL20","doi":"10.4230/LIPICS.CPM.2020.14","ee":"https://doi.org/10.4230/LIPIcs.CPM.2020.14","url":"https://dblp.org/rec/conf/cpm/GawrychowskiGL20"},
"url":"URL#629783"
},
{
"@score":"1",
"@id":"629784",
"info":{"authors":{"author":[{"@pid":"184/8087","text":"Shay Golan 0001"},{"@pid":"38/9892","text":"Tomasz Kociumaka"},{"@pid":"84/3922","text":"Tsvi Kopelowitz"},{"@pid":"02/836","text":"Ely Porat"}]},"title":"The Streaming k-Mismatch Problem - Tradeoffs Between Space and Total Time.","venue":"CPM","pages":"15:1-15:15","year":"2020","type":"Conference and Workshop Papers","access":"open","key":"conf/cpm/GolanKKP20","doi":"10.4230/LIPICS.CPM.2020.15","ee":"https://doi.org/10.4230/LIPIcs.CPM.2020.15","url":"https://dblp.org/rec/conf/cpm/GolanKKP20"},
"url":"URL#629784"
},
{
"@score":"1",
"@id":"629785",
"info":{"authors":{"author":[{"@pid":"213/7336","text":"Garance Gourdel"},{"@pid":"38/9892","text":"Tomasz Kociumaka"},{"@pid":"83/7216","text":"Jakub Radoszewski"},{"@pid":"99/3746","text":"Tatiana Starikovskaya"}]},"title":"Approximating Longest Common Substring with k mismatches - Theory and Practice.","venue":"CPM","pages":"16:1-16:15","year":"2020","type":"Conference and Workshop Papers","access":"open","key":"conf/cpm/GourdelKRS20","doi":"10.4230/LIPICS.CPM.2020.16","ee":"https://doi.org/10.4230/LIPIcs.CPM.2020.16","url":"https://dblp.org/rec/conf/cpm/GourdelKRS20"},
"url":"URL#629785"
},
{
"@score":"1",
"@id":"629786",
"info":{"authors":{"author":[{"@pid":"217/1728","text":"Niels Grüttemeier"},{"@pid":"69/1771","text":"Christian Komusiewicz"},{"@pid":"256/7583","text":"Nils Morawietz"},{"@pid":"223/1925","text":"Frank Sommer"}]},"title":"String Factorizations Under Various Collision Constraints.","venue":"CPM","pages":"17:1-17:14","year":"2020","type":"Conference and Workshop Papers","access":"open","key":"conf/cpm/GruttemeierKMS20","doi":"10.4230/LIPICS.CPM.2020.17","ee":"https://doi.org/10.4230/LIPIcs.CPM.2020.17","url":"https://dblp.org/rec/conf/cpm/GruttemeierKMS20"},
"url":"URL#629786"
},
{
"@score":"1",
"@id":"629787",
"info":{"authors":{"author":{"@pid":"71/576","text":"Thore Husfeldt"}},"title":"Algebraic Algorithms for Finding Patterns in Graphs (Invited Talk).","venue":"CPM","pages":"1:1-1:1","year":"2020","type":"Conference and Workshop Papers","access":"open","key":"conf/cpm/Husfeldt20","doi":"10.4230/LIPICS.CPM.2020.1","ee":"https://doi.org/10.4230/LIPIcs.CPM.2020.1","url":"https://dblp.org/rec/conf/cpm/Husfeldt20"},
"url":"URL#629787"
},
{
"@score":"1",
"@id":"629788",
"info":{"authors":{"author":[{"@pid":"264/9576","text":"Aleksander Kedzierski"},{"@pid":"83/7216","text":"Jakub Radoszewski"}]},"title":"k-Approximate Quasiperiodicity under Hamming and Edit Distance.","venue":"CPM","pages":"18:1-18:15","year":"2020","type":"Conference and Workshop Papers","access":"open","key":"conf/cpm/KedzierskiR20","doi":"10.4230/LIPICS.CPM.2020.18","ee":"https://doi.org/10.4230/LIPIcs.CPM.2020.18","url":"https://dblp.org/rec/conf/cpm/KedzierskiR20"},
"url":"URL#629788"
},
{
"@score":"1",
"@id":"629789",
"info":{"authors":{"author":[{"@pid":"234/8033","text":"Evangelos Kipouridis"},{"@pid":"87/172","text":"Kostas Tsichlas"}]},"title":"Longest Common Subsequence on Weighted Sequences.","venue":"CPM","pages":"19:1-19:15","year":"2020","type":"Conference and Workshop Papers","access":"open","key":"conf/cpm/KipouridisT20","doi":"10.4230/LIPICS.CPM.2020.19","ee":"https://doi.org/10.4230/LIPIcs.CPM.2020.19","url":"https://dblp.org/rec/conf/cpm/KipouridisT20"},
"url":"URL#629789"
},
{
"@score":"1",
"@id":"629790",
"info":{"authors":{"author":[{"@pid":"244/8353","text":"Tomohiro Koana"},{"@pid":"133/1147","text":"Vincent Froese"},{"@pid":"n/RolfNiedermeier","text":"Rolf Niedermeier"}]},"title":"Parameterized Algorithms for Matrix Completion with Radius Constraints.","venue":"CPM","pages":"20:1-20:14","year":"2020","type":"Conference and Workshop Papers","access":"open","key":"conf/cpm/KoanaFN20","doi":"10.4230/LIPICS.CPM.2020.20","ee":"https://doi.org/10.4230/LIPIcs.CPM.2020.20","url":"https://dblp.org/rec/conf/cpm/KoanaFN20"},
"url":"URL#629790"
},
{
"@score":"1",
"@id":"629791",
"info":{"authors":{"author":[{"@pid":"129/9119","text":"Dominik Köppl"},{"@pid":"238/8505","text":"Daiki Hashimoto"},{"@pid":"176/8779","text":"Diptarama Hendrian"},{"@pid":"s/AyumiShinohara","text":"Ayumi Shinohara"}]},"title":"In-Place Bijective Burrows-Wheeler Transforms.","venue":"CPM","pages":"21:1-21:15","year":"2020","type":"Conference and Workshop Papers","access":"open","key":"conf/cpm/KopplHHS20","doi":"10.4230/LIPICS.CPM.2020.21","ee":"https://doi.org/10.4230/LIPIcs.CPM.2020.21","url":"https://dblp.org/rec/conf/cpm/KopplHHS20"},
"url":"URL#629791"
},
{
"@score":"1",
"@id":"629792",
"info":{"authors":{"author":[{"@pid":"117/8942","text":"Manuel Lafond"},{"@pid":"z/BinhaiZhu","text":"Binhai Zhu"},{"@pid":"05/886","text":"Peng Zou"}]},"title":"Genomic Problems Involving Copy Number Profiles - Complexity and Algorithms.","venue":"CPM","pages":"22:1-22:15","year":"2020","type":"Conference and Workshop Papers","access":"open","key":"conf/cpm/LafondZZ20","doi":"10.4230/LIPICS.CPM.2020.22","ee":"https://doi.org/10.4230/LIPIcs.CPM.2020.22","url":"https://dblp.org/rec/conf/cpm/LafondZZ20"},
"url":"URL#629792"
},
{
"@score":"1",
"@id":"629793",
"info":{"authors":{"author":[{"@pid":"77/2752","text":"Veli Mäkinen"},{"@pid":"118/0896","text":"Kristoffer Sahlin"}]},"title":"Chaining with Overlaps Revisited.","venue":"CPM","pages":"25:1-25:12","year":"2020","type":"Conference and Workshop Papers","access":"open","key":"conf/cpm/MakinenS20","doi":"10.4230/LIPICS.CPM.2020.25","ee":"https://doi.org/10.4230/LIPIcs.CPM.2020.25","url":"https://dblp.org/rec/conf/cpm/MakinenS20"},
"url":"URL#629793"
},
{
"@score":"1",
"@id":"629794",
"info":{"authors":{"author":[{"@pid":"250/2110","text":"Kotaro Matsuda"},{"@pid":"74/5752","text":"Kunihiko Sadakane"},{"@pid":"99/3746","text":"Tatiana Starikovskaya"},{"@pid":"266/8956","text":"Masakazu Tateshita"}]},"title":"Compressed Orthogonal Search on Suffix Arrays with Applications to Range LCP.","venue":"CPM","pages":"23:1-23:13","year":"2020","type":"Conference and Workshop Papers","access":"open","key":"conf/cpm/MatsudaSST20","doi":"10.4230/LIPICS.CPM.2020.23","ee":"https://doi.org/10.4230/LIPIcs.CPM.2020.23","url":"https://dblp.org/rec/conf/cpm/MatsudaSST20"},
"url":"URL#629794"
},
{
"@score":"1",
"@id":"629795",
"info":{"authors":{"author":[{"@pid":"m/JIanMunro","text":"J. Ian Munro"},{"@pid":"n/GonzaloNavarro","text":"Gonzalo Navarro"},{"@pid":"n/YakovNekrich","text":"Yakov Nekrich"}]},"title":"Text Indexing and Searching in Sublinear Time.","venue":"CPM","pages":"24:1-24:15","year":"2020","type":"Conference and Workshop Papers","access":"open","key":"conf/cpm/MunroNN20","doi":"10.4230/LIPICS.CPM.2020.24","ee":"https://doi.org/10.4230/LIPIcs.CPM.2020.24","url":"https://dblp.org/rec/conf/cpm/MunroNN20"},
"url":"URL#629795"
},
{
"@score":"1",
"@id":"629796",
"info":{"authors":{"author":[{"@pid":"234/2418","text":"Katsuhito Nakashima"},{"@pid":"225/4714","text":"Noriki Fujisato"},{"@pid":"176/8779","text":"Diptarama Hendrian"},{"@pid":"118/6656","text":"Yuto Nakashima"},{"@pid":"62/4416","text":"Ryo Yoshinaka"},{"@pid":"88/1129","text":"Shunsuke Inenaga"},{"@pid":"44/2355","text":"Hideo Bannai"},{"@pid":"s/AyumiShinohara","text":"Ayumi Shinohara"},{"@pid":"35/1544","text":"Masayuki Takeda"}]},"title":"DAWGs for Parameterized Matching - Online Construction and Related Indexing Structures.","venue":"CPM","pages":"26:1-26:14","year":"2020","type":"Conference and Workshop Papers","access":"open","key":"conf/cpm/NakashimaFHNYIB20","doi":"10.4230/LIPICS.CPM.2020.26","ee":"https://doi.org/10.4230/LIPIcs.CPM.2020.26","url":"https://dblp.org/rec/conf/cpm/NakashimaFHNYIB20"},
"url":"URL#629796"
},
{
"@score":"1",
"@id":"629797",
"info":{"authors":{"author":[{"@pid":"260/0197","text":"Stav Ben-Nun"},{"@pid":"184/8087","text":"Shay Golan 0001"},{"@pid":"38/9892","text":"Tomasz Kociumaka"},{"@pid":"260/0179","text":"Matan Kraus"}]},"title":"Time-Space Tradeoffs for Finding a Long Common Substring.","venue":"CPM","pages":"5:1-5:14","year":"2020","type":"Conference and Workshop Papers","access":"open","key":"conf/cpm/Nun0KK20","doi":"10.4230/LIPICS.CPM.2020.5","ee":"https://doi.org/10.4230/LIPIcs.CPM.2020.5","url":"https://dblp.org/rec/conf/cpm/Nun0KK20"},
"url":"URL#629797"
},
{
"@score":"1",
"@id":"629798",
"info":{"authors":{"author":{"@pid":"242/3319","text":"Julian Pape-Lange"}},"title":"On Extensions of Maximal Repeats in Compressed Strings.","venue":"CPM","pages":"27:1-27:13","year":"2020","type":"Conference and Workshop Papers","access":"open","key":"conf/cpm/Pape-Lange20","doi":"10.4230/LIPICS.CPM.2020.27","ee":"https://doi.org/10.4230/LIPIcs.CPM.2020.27","url":"https://dblp.org/rec/conf/cpm/Pape-Lange20"},
"url":"URL#629798"
},
{
"@score":"1",
"@id":"629799",
"info":{"authors":{"author":[{"@pid":"258/1080","text":"Nathan Schaar"},{"@pid":"133/1147","text":"Vincent Froese"},{"@pid":"n/RolfNiedermeier","text":"Rolf Niedermeier"}]},"title":"Faster Binary Mean Computation Under Dynamic Time Warping.","venue":"CPM","pages":"28:1-28:13","year":"2020","type":"Conference and Workshop Papers","access":"open","key":"conf/cpm/SchaarFN20","doi":"10.4230/LIPICS.CPM.2020.28","ee":"https://doi.org/10.4230/LIPIcs.CPM.2020.28","url":"https://dblp.org/rec/conf/cpm/SchaarFN20"},
"url":"URL#629799"
},
{
"@score":"1",
"@id":"629800",
"info":{"authors":{"author":{"@pid":"78/11210","text":"Przemyslaw Uznanski"}},"title":"Approximating Text-To-Pattern Distance via Dimensionality Reduction.","venue":"CPM","pages":"29:1-29:11","year":"2020","type":"Conference and Workshop Papers","access":"open","key":"conf/cpm/Uznanski20","doi":"10.4230/LIPICS.CPM.2020.29","ee":"https://doi.org/10.4230/LIPIcs.CPM.2020.29","url":"https://dblp.org/rec/conf/cpm/Uznanski20"},
"url":"URL#629800"
},
{
"@score":"1",
"@id":"629801",
"info":{"title":"Front Matter, Table of Contents, Preface, Conference Organization.","venue":"CPM","pages":"0:1-0:16","year":"2020","type":"Conference and Workshop Papers","access":"open","key":"conf/cpm/X20","doi":"10.4230/LIPICS.CPM.2020.0","ee":"https://doi.org/10.4230/LIPIcs.CPM.2020.0","url":"https://dblp.org/rec/conf/cpm/X20"},
"url":"URL#629801"
},
{
"@score":"1",
"@id":"761153",
"info":{"authors":{"author":[{"@pid":"96/705","text":"Inge Li Gørtz"},{"@pid":"93/2346","text":"Oren Weimann"}]},"title":"31st Annual Symposium on Combinatorial Pattern Matching, CPM 2020, June 17-19, 2020, Copenhagen, Denmark.","venue":["CPM","LIPIcs"],"volume":"161","publisher":"Schloss Dagstuhl - Leibniz-Zentrum für Informatik","year":"2020","type":"Editorship","key":"conf/cpm/2020","ee":"https://www.dagstuhl.de/dagpub/978-3-95977-149-8","url":"https://dblp.org/rec/conf/cpm/2020"},
"url":"URL#761153"
}
]
}
}
}
